{
  "schema_version": 1,
  "calendar": "julian_old_calendar",
  "policy": "same_language_source_only",
  "weekday_prokeimena": {
    "0": {
      "tone": 4,
      "title": {
        "ar": "البروكيمنن — اللحن الرابع",
        "en": "Prokeimenon — Tone 4",
        "el": "Προκείμενον — Ἦχος δ΄"
      },
      "reference": {
        "ar": "مزمور 103:4، 1",
        "en": "Psalm 103:4, 1 (LXX)",
        "el": "Ψαλμός 103:4, 1"
      },
      "body": {
        "ar": "الصانع ملائكته أرواحًا وخدامه لهيب نار.\nباركي يا نفسي الرب. يا رب إلهي لقد عظمت جدًا.",
        "en": "He makes His angels spirits, and His ministers a flame of fire.\nBless the Lord, O my soul! O Lord my God, You are very great!",
        "el": "Ὁ ποιῶν τοὺς ἀγγέλους αὐτοῦ πνεύματα, καὶ τοὺς λειτουργοὺς αὐτοῦ πυρὸς φλόγα.\nΕὐλόγει, ἡ ψυχή μου, τὸν Κύριον· Κύριε ὁ Θεός μου, ἐμεγαλύνθης σφόδρα."
      }
    },
    "1": {
      "tone": 7,
      "title": {
        "ar": "البروكيمنن — اللحن السابع",
        "en": "Prokeimenon — Tone 7",
        "el": "Προκείμενον — Ἦχος βαρύς"
      },
      "reference": {
        "ar": "مزمور 63:11، 2",
        "en": "Psalm 63:11, 2 (LXX)",
        "el": "Ψαλμός 63:11, 2"
      },
      "body": {
        "ar": "يفرح الصديق بالرب ويتكل عليه.\nاستمع يا الله إلى صوتي في تضرعي إليك.",
        "en": "The righteous shall rejoice in the Lord and shall hope in Him.\nHear my voice, O God, when I pray to You.",
        "el": "Εὐφρανθήσεται δίκαιος ἐν Κυρίῳ καὶ ἐλπιεῖ ἐπ᾽ αὐτόν.\nΕἰσάκουσον, ὁ Θεός, τῆς φωνῆς μου ἐν τῷ δέεσθαί με πρὸς σέ."
      }
    },
    "2": {
      "tone": 3,
      "title": {
        "ar": "البروكيمنن — اللحن الثالث",
        "en": "Prokeimenon — Tone 3",
        "el": "Προκείμενον — Ἦχος γ΄"
      },
      "reference": {
        "ar": "لوقا 1:46–48",
        "en": "Luke 1:46–48",
        "el": "Λουκᾶς 1:46–48"
      },
      "body": {
        "ar": "تعظم نفسي الرب وتبتهج روحي بالله مخلصي.\nلأنه نظر إلى تواضع أمته، فها منذ الآن تطوبني جميع الأجيال.",
        "en": "My soul magnifies the Lord, and my spirit rejoices in God my Savior.\nFor He has regarded the low estate of His handmaiden; for behold, henceforth all generations will call me blessed.",
        "el": "Μεγαλύνει ἡ ψυχή μου τὸν Κύριον, καὶ ἠγαλλίασε τὸ πνεῦμά μου ἐπὶ τῷ Θεῷ τῷ σωτῆρί μου.\nὍτι ἐπέβλεψεν ἐπὶ τὴν ταπείνωσιν τῆς δούλης αὐτοῦ· ἰδοὺ γὰρ ἀπὸ τοῦ νῦν μακαριοῦσί με πᾶσαι αἱ γενεαί."
      }
    },
    "3": {
      "tone": 8,
      "title": {
        "ar": "البروكيمنن — اللحن الثامن",
        "en": "Prokeimenon — Tone 8",
        "el": "Προκείμενον — Ἦχος πλ. δ΄"
      },
      "reference": {
        "ar": "مزمور 18:5، 2",
        "en": "Psalm 18:5, 2 (LXX)",
        "el": "Ψαλμός 18:5, 2"
      },
      "body": {
        "ar": "إلى كل الأرض خرج صوتهم وإلى أقاصي المسكونة أقوالهم.\nالسماوات تحدث بمجد الله والفلك يخبر بعمل يديه.",
        "en": "Their proclamation has gone out into all the earth, and their words to the ends of the universe.\nThe heavens declare the glory of God, and the firmament proclaims the work of His hands.",
        "el": "Εἰς πᾶσαν τὴν γῆν ἐξῆλθεν ὁ φθόγγος αὐτῶν, καὶ εἰς τὰ πέρατα τῆς οἰκουμένης τὰ ῥήματα αὐτῶν.\nΟἱ οὐρανοὶ διηγοῦνται δόξαν Θεοῦ, ποίησιν δὲ χειρῶν αὐτοῦ ἀναγγέλλει τὸ στερέωμα."
      }
    },
    "4": {
      "tone": 7,
      "title": {
        "ar": "البروكيمنن — اللحن السابع",
        "en": "Prokeimenon — Tone 7",
        "el": "Προκείμενον — Ἦχος βαρύς"
      },
      "reference": {
        "ar": "مزمور 98:5، 1",
        "en": "Psalm 98:5, 1 (LXX)",
        "el": "Ψαλμός 98:5, 1"
      },
      "body": {
        "ar": "ارفعوا الرب إلهنا واسجدوا عند موطئ قدميه فإنه قدوس.\nالرب قد ملك، فترتعد الشعوب.",
        "en": "Exalt the Lord our God, and worship at His footstool, for He is holy.\nThe Lord reigns; let the peoples tremble.",
        "el": "Ὑψοῦτε Κύριον τὸν Θεὸν ἡμῶν καὶ προσκυνεῖτε τῷ ὑποποδίῳ τῶν ποδῶν αὐτοῦ, ὅτι ἅγιός ἐστι.\nὉ Κύριος ἐβασίλευσεν, ὀργιζέσθωσαν λαοί."
      }
    },
    "5": {
      "tone": 8,
      "title": {
        "ar": "البروكيمنن — اللحن الثامن",
        "en": "Prokeimenon — Tone 8",
        "el": "Προκείμενον — Ἦχος πλ. δ΄"
      },
      "reference": {
        "ar": "مزمور 31:11، 1",
        "en": "Psalm 31:11, 1 (LXX)",
        "el": "Ψαλμός 31:11, 1"
      },
      "body": {
        "ar": "افرحوا بالرب وابتهجوا يا أيها الصديقون.\nطوبى للذين غفرت آثامهم وسترت خطاياهم.",
        "en": "Be glad in the Lord and rejoice, O righteous.\nBlessed are those whose transgressions are forgiven and whose sins are covered.",
        "el": "Εὐφράνθητε ἐπὶ Κύριον καὶ ἀγαλλιᾶσθε, δίκαιοι.\nΜακάριοι ὧν ἀφέθησαν αἱ ἀνομίαι καὶ ὧν ἐπεκαλύφθησαν αἱ ἁμαρτίαι."
      }
    }
  },
  "fixed_feasts": {
    "07-02": {
      "id": "placing_robe_theotokos_blachernae",
      "name": {
        "ar": "وضع ثوب والدة الإله في كنيسة بلاشيرن",
        "en": "Placing of the Honorable Robe of the Most Holy Theotokos at Blachernae",
        "el": "Κατάθεσις τῆς Τιμίας Ἐσθῆτος τῆς Θεοτόκου ἐν Βλαχέρναις"
      },
      "troparion": {
        "ar": "يا والدة الإله الدائمة البتولية وستر البشر، لقد وهبت لمدينتك ثوبك وزنار جسدك الطاهر وشاحًا حريزًا، اللذين بمولدك الذي بغير زرع استمرا بغير فساد، لأن بك تتجدد الطبيعة والزمان. فلذلك نبتهل إليك أن تمنحي السلام لمدينتك ولنفوسنا الرحمة العظمى.",
        "en": "O Ever-Virgin Mother of God, shelter of mankind, thou hast given a powerful legacy to thy people, thine immaculate body’s tunic and sash which remain incorrupt through thy pure childbirth. For in thee time and nature are renewed, and we implore thee to obtain peace for the world and great mercy for our souls.",
        "el": "Θεοτόκε ἀειπάρθενε, τῶν ἀνθρώπων ἡ σκέπη, Ἐσθῆτα καὶ Ζώνην τοῦ ἀχράντου σου σώματος, κραταιὰν τῇ πόλει σου περιβολὴν ἐδωρήσω, τῷ ἀσπόρῳ τόκῳ σου ἄφθαρτα διαμείναντα· ἐπὶ σοὶ γὰρ καὶ φύσις καινοτομεῖται καὶ χρόνος. Διὸ δυσωποῦμέν σε, εἰρήνην τῇ οἰκουμένῃ δωρήσασθαι καὶ ταῖς ψυχαῖς ἡμῶν τὸ μέγα ἔλεος."
      },
      "kontakion": {
        "ar": "أيتها النقية المنعم عليها من الله، إن ثوبك الموقر الذي به انحجب جسدك الطاهر قد منحته لجميع المؤمنين سربالًا لعدم الفساد وسترًا إلهيًا للبشر. فنحن نعيد لوضعه بشوق ونهتف بإيمان صارخين: السلام عليك أيتها البتول فخر المسيحيين.",
        "en": "Thou hast given the covering of thy pure body as an incorrupt garment for all the faithful, and as shelter for all mankind, O pure Lady, Mother of God. We celebrate its placing in Blachernae and cry to thee with fear and love: O Virgin, boast of Christians, rejoice.",
        "el": "Περιβολὴν πᾶσι πιστοῖς ἀφθαρσίας, θεοχαρίτωτε Ἁγνὴ ἐδωρήσω, τὴν ἱερὰν Ἐσθῆτά σου, μεθ᾽ ἧς τὸ ἱερόν σου σῶμα ἐσκέπασας, σκέπη θεία ἀνθρώπων· ἧς περ τὴν κατάθεσιν ἑορτάζομεν πόθῳ, καὶ ἐκβοῶντες κράζομεν πιστῶς· Χαῖρε Παρθένε, Χριστιανῶν τὸ καύχημα."
      },
      "prokeimenon": {
        "tone": 3,
        "title": {
          "ar": "البروكيمنن — اللحن الثالث",
          "en": "Prokeimenon — Tone 3",
          "el": "Προκείμενον — Ἦχος γ΄"
        },
        "reference": {
          "ar": "لوقا 1:46، 48",
          "en": "Luke 1:46, 48",
          "el": "Λουκᾶς 1:46, 48"
        },
        "body": {
          "ar": "تعظم نفسي الرب.\nلأنه نظر إلى تواضع أمته.",
          "en": "My soul magnifies the Lord.\nFor He has regarded the low estate of His handmaiden.",
          "el": "Μεγαλύνει ἡ ψυχή μου τὸν Κύριον.\nὍτι ἐπέβλεψεν ἐπὶ τὴν ταπείνωσιν τῆς δούλης αὐτοῦ."
        }
      },
      "sources": {
        "ar": {
          "source_id": "antioch_archdiocese_tripoli_ar",
          "url": "https://archtripoli.org/Karma/2023/July/2"
        },
        "en": {
          "source_id": "akroasis_small_menaion_english",
          "url": "https://akroasis.org/texts-and-resources/small-menaion/small-menaion-july/"
        },
        "el": {
          "source_id": "goarch_online_chapel_greek",
          "url": "https://www.goarch.org/chapel/saints?contentid=187&language=el"
        }
      }
    }
  },
  "weekly_sources": {
    "ar": {
      "source_id": "antioch_archdiocese_tripoli_ar",
      "url": "https://archtripoli.org/"
    },
    "en": {
      "source_id": "goarch_online_chapel",
      "url": "https://www.goarch.org/chapel"
    },
    "el": {
      "source_id": "goarch_online_chapel_greek",
      "url": "https://www.goarch.org/chapel"
    }
  }
}
